shiny_calendar/__init__.py
shiny_calendar/py.typed
shiny_calendar/shiny_calendar.py
shiny_calendar/distjs/index.js
shiny_calendar-0.2.0.dist-info/METADATA
shiny_calendar-0.2.0.dist-info/WHEEL
shiny_calendar-0.2.0.dist-info/licenses/LICENSE
shiny_calendar-0.2.0.dist-info/RECORD
