Metadata-Version: 2.4
Name: shiny-calendar
Version: 0.2.0
Summary: A calendar component for Python Shiny using FullCalendar
Project-URL: GitHub, https://github.com/gcirio/shiny-calendar
Author-email: Gabriel Cirio <gabriel.cirio@gmail.com>
License-Expression: MIT
License-File: LICENSE
Requires-Python: >=3.9
Requires-Dist: shiny>=0.6.0
